huetracer/__init__.py
huetracer/cci.py
huetracer/harmony.py
huetracer/plot.py
huetracer/statistics.py
huetracer/vae.py
huetracer-0.0.11.dist-info/licenses/LICENSE
huetracer-0.0.11.dist-info/METADATA
huetracer-0.0.11.dist-info/WHEEL
huetracer-0.0.11.dist-info/top_level.txt
huetracer-0.0.11.dist-info/RECORD
