Metadata-Version: 2.4
Name: huetracer
Version: 0.0.11
Summary: Analyze cell-cell interaction with spatial transcriptome data.
Home-page: https://github.com/MANO-B/HueTracer
Author: Masachika Ikegami
Author-email: ikegamitky@gmail.com
Classifier: Programming Language :: Python :: 3
Classifier: License :: OSI Approved :: MIT License
Requires-Python: >=3.7
License-File: LICENSE
Requires-Dist: numpy
Requires-Dist: matplotlib
Requires-Dist: scipy
Requires-Dist: tqdm
Requires-Dist: scanpy
Requires-Dist: scikit-image
Requires-Dist: opencv-python
Requires-Dist: pandas
Requires-Dist: torch
Requires-Dist: plotly
Requires-Dist: matplotlib
Dynamic: author
Dynamic: author-email
Dynamic: classifier
Dynamic: home-page
Dynamic: license-file
Dynamic: requires-dist
Dynamic: requires-python
Dynamic: summary
